bbcstyle/__init__.py
bbcstyle/finalise_plot.py
bbcstyle/theme.py
bbcstyle-0.1.1.dist-info/licenses/LICENSE
bbcstyle-0.1.1.dist-info/METADATA
bbcstyle-0.1.1.dist-info/WHEEL
bbcstyle-0.1.1.dist-info/top_level.txt
bbcstyle-0.1.1.dist-info/RECORD
