Metadata-Version: 2.4
Name: bbcstyle
Version: 0.1.1
Summary: BBC-inspired Matplotlib/Seaborn theme for clean, publication-ready charts.
Author: Alessandro Tomassini
License-Expression: MIT
Project-URL: Homepage, https://github.com/ale-tom/bbcstyle
Project-URL: Issues, https://github.com/ale-tom/bbcstyle/issues
Project-URL: Changelog, https://github.com/ale-tom/bbcstyle/releases
Project-URL: Contact, https://github.com/ale-tom/bbcstyle/issues/new/choose
Keywords: matplotlib,seaborn,theme,visualization,bbc
Classifier: Programming Language :: Python :: 3
Classifier: Programming Language :: Python :: 3 :: Only
Classifier: Programming Language :: Python :: 3.8
Classifier: Programming Language :: Python :: 3.9
Classifier: Programming Language :: Python :: 3.10
Classifier: Programming Language :: Python :: 3.11
Classifier: Programming Language :: Python :: 3.12
Classifier: Topic :: Scientific/Engineering :: Visualization
Requires-Python: >=3.8
License-File: LICENSE
Requires-Dist: matplotlib>=3.5
Requires-Dist: seaborn>=0.12
Dynamic: license-file
